[1,0,0,[["cc.JsonAsset",["_name","json"],1]],[[0,0,1,3]],[[0,"LevelGeneral",[{"备注":"","Id":"","Column2":"","MapId":"","ThumbnailId":"","Column5":"","WinRewardDrawId":"","LoseRewardDrawId":""},{"备注":"","Id":"","Column2":"","MapId":"","ThumbnailId":"","Column5":"","WinRewardDrawId":"","LoseRewardDrawId":""},{"备注":"","Id":"Test_001","Column2":"","MapId":"","ThumbnailId":"","Column5":"","WinRewardDrawId":"","LoseRewardDrawId":""},{"备注":"","Id":"","Column2":"","MapId":"","ThumbnailId":"","Column5":"","WinRewardDrawId":"","LoseRewardDrawId":""},{"备注":"","Id":"","Column2":"","MapId":"","ThumbnailId":"","Column5":"","WinRewardDrawId":"","LoseRewardDrawId":""},{"备注":"","Id":"","Column2":"","MapId":"","ThumbnailId":"","Column5":"","WinRewardDrawId":"","LoseRewardDrawId":""},{"备注":"","Id":"1","Column2":"","MapId":"002","ThumbnailId":"","Column5":"","WinRewardDrawId":"","LoseRewardDrawId":""},{"备注":"","Id":"2","Column2":"","MapId":"002","ThumbnailId":"","Column5":"","WinRewardDrawId":"","LoseRewardDrawId":""},{"备注":"","Id":"3","Column2":"","MapId":"003","ThumbnailId":"","Column5":"","WinRewardDrawId":"","LoseRewardDrawId":""},{"备注":"","Id":"4","Column2":"","MapId":"003","ThumbnailId":"","Column5":"","WinRewardDrawId":"","LoseRewardDrawId":""},{"备注":"","Id":"5","Column2":"","MapId":"004","ThumbnailId":"","Column5":"","WinRewardDrawId":"","LoseRewardDrawId":""},{"备注":"","Id":"6","Column2":"","MapId":"004","ThumbnailId":"","Column5":"","WinRewardDrawId":"","LoseRewardDrawId":""},{"备注":"","Id":"7","Column2":"","MapId":"002","ThumbnailId":"","Column5":"","WinRewardDrawId":"","LoseRewardDrawId":""},{"备注":"","Id":"8","Column2":"","MapId":"002","ThumbnailId":"","Column5":"","WinRewardDrawId":"","LoseRewardDrawId":""},{"备注":"","Id":"9","Column2":"","MapId":"002","ThumbnailId":"","Column5":"","WinRewardDrawId":"","LoseRewardDrawId":""},{"备注":"","Id":"10","Column2":"","MapId":"002","ThumbnailId":"","Column5":"","WinRewardDrawId":"","LoseRewardDrawId":""}]]],0,0,[],[],[]]
